clarivuexai/__init__.py
clarivuexai/cli.py
clarivuexai/core/__init__.py
clarivuexai/core/base.py
clarivuexai/core/registry.py
clarivuexai/core/utils.py
clarivuexai/data/__init__.py
clarivuexai/data/image.py
clarivuexai/data/tabular.py
clarivuexai/data/text.py
clarivuexai/data/timeseries.py
clarivuexai/explainers/__init__.py
clarivuexai/explainers/counterfactual.py
clarivuexai/explainers/feature_importance.py
clarivuexai/explainers/integrated_gradients.py
clarivuexai/explainers/lime_explainers.py
clarivuexai/explainers/shap_explainers.py
clarivuexai/models/__init__.py
clarivuexai/models/custom_models.py
clarivuexai/models/pytorch_models.py
clarivuexai/models/sklearn_models.py
clarivuexai/models/tensorflow_models.py
clarivuexai/visualization/__init__.py
clarivuexai/visualization/dashboards.py
clarivuexai/visualization/interactive.py
clarivuexai/visualization/plots.py
clarivuexai-0.1.0.dist-info/licenses/LICENSE
clarivuexai-0.1.0.dist-info/METADATA
clarivuexai-0.1.0.dist-info/WHEEL
clarivuexai-0.1.0.dist-info/entry_points.txt
clarivuexai-0.1.0.dist-info/top_level.txt
clarivuexai-0.1.0.dist-info/RECORD
