Metadata-Version: 2.4
Name: clarivuexai
Version: 0.1.0
Summary: A unified framework for explainable AI
Home-page: https://github.com/yourusername/clarivuexai
Author: wizcodes
Author-email: wizcodes <wizcodes12@gmail.com>
License: MIT
Project-URL: Homepage, https://github.com/wizcodes12/clarivuexai
Project-URL: Bug Tracker, https://github.com/wizcodes12/clarivuexai/issues
Project-URL: Documentation, https://clarivuexai.readthedocs.io/
Classifier: Programming Language :: Python :: 3
Classifier: License :: OSI Approved :: MIT License
Classifier: Operating System :: OS Independent
Classifier: Development Status :: 3 - Alpha
Classifier: Intended Audience :: Science/Research
Classifier: Topic :: Scientific/Engineering :: Artificial Intelligence
Requires-Python: >=3.8
License-File: LICENSE
Requires-Dist: numpy>=1.19.0
Requires-Dist: pandas>=1.1.0
Requires-Dist: scikit-learn>=0.24.0
Requires-Dist: matplotlib>=3.3.0
Requires-Dist: seaborn>=0.11.0
Requires-Dist: plotly>=5.0.0
Requires-Dist: shap>=0.39.0
Requires-Dist: lime>=0.2.0
Provides-Extra: tensorflow
Requires-Dist: tensorflow>=2.4.0; extra == "tensorflow"
Provides-Extra: torch
Requires-Dist: torch>=1.8.0; extra == "torch"
Requires-Dist: torchvision>=0.9.0; extra == "torch"
Provides-Extra: dev
Requires-Dist: pytest>=6.0.0; extra == "dev"
Requires-Dist: pytest-cov>=2.12.0; extra == "dev"
Requires-Dist: sphinx>=4.0.0; extra == "dev"
Requires-Dist: sphinx-rtd-theme>=0.5.0; extra == "dev"
Requires-Dist: black>=21.5b2; extra == "dev"
Requires-Dist: isort>=5.9.0; extra == "dev"
Requires-Dist: flake8>=3.9.0; extra == "dev"
Provides-Extra: all
Requires-Dist: tensorflow>=2.4.0; extra == "all"
Requires-Dist: torch>=1.8.0; extra == "all"
Requires-Dist: torchvision>=0.9.0; extra == "all"
Dynamic: author
Dynamic: home-page
Dynamic: license-file
Dynamic: requires-python
